{
  "hash": "73b96510",
  "configHash": "525bb6a5",
  "lockfileHash": "e3b0c442",
  "browserHash": "d5379c59",
  "optimized": {
    "vue": {
      "src": "../../../node_modules/vue/dist/vue.runtime.esm-bundler.js",
      "file": "vue.js",
      "fileHash": "a21c570f",
      "needsInterop": false
    },
    "vitepress > @vue/devtools-api": {
      "src": "../../../node_modules/@vue/devtools-api/dist/index.js",
      "file": "vitepress___@vue_devtools-api.js",
      "fileHash": "507f2643",
      "needsInterop": false
    },
    "vitepress > @vueuse/core": {
      "src": "../../../node_modules/@vueuse/core/index.mjs",
      "file": "vitepress___@vueuse_core.js",
      "fileHash": "5856c417",
      "needsInterop": false
    }
  },
  "chunks": {
    "chunk-JWA4H7QR": {
      "file": "chunk-JWA4H7QR.js"
    }
  }
}